moq/__init__.py
moq/cli.py
moq/moq.py
moq-0.1.0.dist-info/AUTHORS.rst
moq-0.1.0.dist-info/LICENSE
moq-0.1.0.dist-info/METADATA
moq-0.1.0.dist-info/WHEEL
moq-0.1.0.dist-info/entry_points.txt
moq-0.1.0.dist-info/top_level.txt
moq-0.1.0.dist-info/RECORD
